pyramid_storage/__init__.py
pyramid_storage/exceptions.py
pyramid_storage/extensions.py
pyramid_storage/gcloud.py
pyramid_storage/interfaces.py
pyramid_storage/local.py
pyramid_storage/registry.py
pyramid_storage/s3.py
pyramid_storage/testing.py
pyramid_storage/utils.py
pyramid_storage-1.3.2.dist-info/LICENSE.txt
pyramid_storage-1.3.2.dist-info/METADATA
pyramid_storage-1.3.2.dist-info/WHEEL
pyramid_storage-1.3.2.dist-info/top_level.txt
pyramid_storage-1.3.2.dist-info/RECORD
