Metadata-Version: 2.1
Name: pyramid_storage
Version: 1.3.2
Summary: File storage package for Pyramid
Author-email: Dan Jacob <danjac354@gmail.com>
License: Copyright (c) 2013 by Dan Jacob.
Project-URL: Repository, https://github.com/danjac/pyramid_storage/
Keywords: web services
Classifier: Programming Language :: Python
Classifier: Programming Language :: Python :: 3
Classifier: Topic :: Internet :: WWW/HTTP
Classifier: Topic :: Internet :: WWW/HTTP :: WSGI :: Application
Classifier: License :: OSI Approved :: BSD License
Classifier: Intended Audience :: Developers
Classifier: Framework :: Pyramid
Classifier: Operating System :: OS Independent
License-File: LICENSE.txt
Requires-Dist: pyramid
Provides-Extra: dev
Requires-Dist: ruff ; extra == 'dev'
Requires-Dist: pytest ; extra == 'dev'
Provides-Extra: docs
Requires-Dist: Sphinx ; extra == 'docs'
Requires-Dist: docutils ; extra == 'docs'
Requires-Dist: repoze.sphinx.autointerface ; extra == 'docs'
Provides-Extra: gcloud
Requires-Dist: google-cloud-storage ; extra == 'gcloud'
Provides-Extra: s3
Requires-Dist: boto ; extra == 's3'
